azure/mgmt/playwright/__init__.py
azure/mgmt/playwright/_client.py
azure/mgmt/playwright/_configuration.py
azure/mgmt/playwright/_patch.py
azure/mgmt/playwright/_version.py
azure/mgmt/playwright/py.typed
azure/mgmt/playwright/_utils/__init__.py
azure/mgmt/playwright/_utils/model_base.py
azure/mgmt/playwright/_utils/serialization.py
azure/mgmt/playwright/aio/__init__.py
azure/mgmt/playwright/aio/_client.py
azure/mgmt/playwright/aio/_configuration.py
azure/mgmt/playwright/aio/_patch.py
azure/mgmt/playwright/aio/operations/__init__.py
azure/mgmt/playwright/aio/operations/_operations.py
azure/mgmt/playwright/aio/operations/_patch.py
azure/mgmt/playwright/models/__init__.py
azure/mgmt/playwright/models/_enums.py
azure/mgmt/playwright/models/_models.py
azure/mgmt/playwright/models/_patch.py
azure/mgmt/playwright/operations/__init__.py
azure/mgmt/playwright/operations/_operations.py
azure/mgmt/playwright/operations/_patch.py
azure_mgmt_playwright-1.0.0.dist-info/licenses/LICENSE
azure_mgmt_playwright-1.0.0.dist-info/METADATA
azure_mgmt_playwright-1.0.0.dist-info/WHEEL
azure_mgmt_playwright-1.0.0.dist-info/top_level.txt
azure_mgmt_playwright-1.0.0.dist-info/RECORD
